classversioning/__init__.py
classversioning/header.py
classversioning/meta/__init__.py
classversioning/meta/cachingversionedinitmeta.py
classversioning/meta/versionedinitmeta.py
classversioning/meta/versionedmeta.py
classversioning/py.typed
classversioning/versionedclass.py
classversioning/versionregistry.py
classversioning-0.7.0.dist-info/LICENSE.rst
classversioning-0.7.0.dist-info/METADATA
classversioning-0.7.0.dist-info/WHEEL
classversioning-0.7.0.dist-info/entry_points.txt
classversioning-0.7.0.dist-info/RECORD
