Metadata-Version: 2.1
Name: classversioning
Version: 0.7.0
Summary: Tools for create versioning for classes using inheritance.
Home-page: https://github.com/FongAnthonyM/classversioning
License: MIT
Author: Anthony Fong
Author-email: FongAnthonyM@gmail.com
Requires-Python: >=3.10,<4.0
Classifier: Development Status :: 4 - Beta
Classifier: License :: OSI Approved :: MIT License
Classifier: Programming Language :: Python :: 3
Classifier: Programming Language :: Python :: 3.10
Classifier: Programming Language :: Python :: 3.11
Requires-Dist: baseobjects (>=1.10.0)
Requires-Dist: click (>=8.0.1)
Project-URL: Changelog, https://github.com/FongAnthonyM/classversioning/releases
Project-URL: Documentation, https://classversioning.readthedocs.io
Project-URL: Repository, https://github.com/FongAnthonyM/classversioning
